IBMQuantumExperience/HTTPProxyDigestAuth.py
IBMQuantumExperience/IBMQuantumExperience.py
IBMQuantumExperience/__init__.py
IBMQuantumExperience-2.0.4.dist-info/DESCRIPTION.rst
IBMQuantumExperience-2.0.4.dist-info/METADATA
IBMQuantumExperience-2.0.4.dist-info/RECORD
IBMQuantumExperience-2.0.4.dist-info/WHEEL
IBMQuantumExperience-2.0.4.dist-info/metadata.json
IBMQuantumExperience-2.0.4.dist-info/top_level.txt
