Metadata-Version: 2.0
Name: IBMQuantumExperience
Version: 2.0.4
Summary: A Python library for the Quantum Experience API.
Home-page: https://github.com/QISKit/qiskit-api-py
Author: IBM Research ETX
Author-email: pacom@us.ibm.com
License: Apache-2.0
Keywords: ibm,quantum computer,quantum experience
Platform: UNKNOWN
Classifier: Development Status :: 5 - Production/Stable
Classifier: Intended Audience :: Developers
Classifier: Natural Language :: English
Classifier: License :: OSI Approved :: Apache Software License
Classifier: Programming Language :: Python
Classifier: Programming Language :: Python :: 2
Classifier: Programming Language :: Python :: 2.7
Classifier: Programming Language :: Python :: 3
Classifier: Programming Language :: Python :: 3.4
Classifier: Programming Language :: Python :: 3.5
Classifier: Programming Language :: Python :: 3.6
Requires-Dist: requests
Requires-Dist: requests-ntlm
